Workbook
Name WACC: Inputs!$B$8

Sheet Inputs
A1: ModelGuard Clean Sample
A2: Illustrative structure only; no market data.
A4: Assumption | B4: Value | C4: Unit | D4: Review note
A5: Revenue growth | B5: 0.08 | C5: % | D5: Explicit operating assumption
A6: EBIT margin | B6: 0.22 | C6: % | D6: Flows through the income statement
A7: Tax rate | B7: 0.25 | C7: % | D7: Applied to positive EBIT
A8: WACC | B8: 0.09 | C8: % | D8: DCF discount rate
A9: Terminal growth | B9: 0.025 | C9: % | D9: Must remain below WACC
A10: Base revenue | B10: 1000 | C10: USD mm | D10: Starting point
A11: Model version | B11: 1.0 | D11: Workbook comparison fixture

Sheet Income Statement
A1: Income Statement
A2: Illustrative USD millions
A4: Metric | B4: 2024A | C4: 2025E | D4: 2026E | E4: 2027E
A5: Revenue | B5: =='Inputs'!$B$9 -> 1000 | C5: ==B5*(1+Inputs!$B$5) -> 1080 | D5: ==C5*(1+Inputs!$B$5) -> 1166.4 | E5: ==D5*(1+Inputs!$B$5) -> 1259.712
A6: EBIT | B6: ==B5*Inputs!$B$6 -> 220 | C6: ==C5*Inputs!$B$6 -> 237.6 | D6: ==D5*Inputs!$B$6 -> 256.608 | E6: ==E5*Inputs!$B$6 -> 277.13664
A7: Taxes | B7: ==B6*Inputs!$B$7 -> 55 | C7: ==C6*Inputs!$B$7 -> 59.4 | D7: ==D6*Inputs!$B$7 -> 64.152 | E7: ==E6*Inputs!$B$7 -> 69.28416
A8: Net Income | B8: ==B6-B7 -> 165 | C8: ==C6-C7 -> 178.2 | D8: ==D6-D7 -> 192.456 | E8: ==E6-E7 -> 207.85248

Sheet DCF
A1: DCF Valuation
A2: Illustrative output; not an investment recommendation.
A4: Metric | B4: 2025E | C4: 2026E | D4: 2027E | E4: Formula receipt
A5: Free cash flow | B5: =='Income Statement'!C8 -> 178.2 | C5: =='Income Statement'!D8 -> 192.456 | D5: =='Income Statement'!E8 -> 207.85248 | E5: Net income proxy
A6: Discount factor | B6: ==1/(1+Inputs!$B$8)^1 -> 0.917431 | C6: ==1/(1+Inputs!$B$8)^2 -> 0.84168 | D6: ==1/(1+Inputs!$B$8)^3 -> 0.772183 | E6: WACC
A7: PV of FCF | B7: ==B5*B6 -> 163.55 | C7: ==C5*C6 -> 161.99 | D7: ==D5*D6 -> 160.57 | E7: FCF x discount factor
A8: Terminal value | B8: ==D5*(1+Inputs!$B$9)/(Inputs!$B$8-Inputs!$B$9) -> 3112.13 | E8: Gordon growth
